flowinn/__init__.py
flowinn/config.py
flowinn/version.py
flowinn/mesh/__init__.py
flowinn/mesh/boundary_handler.py
flowinn/mesh/checker.py
flowinn/mesh/geometry.py
flowinn/mesh/mesh.py
flowinn/mesh/meshio.py
flowinn/mesh/sampler.py
flowinn/mesh/visualizer.py
flowinn/models/__init__.py
flowinn/models/model.py
flowinn/physics/RANS2D.py
flowinn/physics/__init__.py
flowinn/physics/boundary_conditions.py
flowinn/physics/steadyNS.py
flowinn/plot/__init__.py
flowinn/plot/plot.py
flowinn/plot/postprocess.py
flowinn/tests/FlowOverAirfoil.py
flowinn/tests/FlowThroughNozzle.py
flowinn/tests/LidDrivenCavity.py
flowinn/tests/MinimalChannelFlow.py
flowinn/tests/__init__.py
flowinn/tests/conftest.py
flowinn/tests/test_geometries.py
flowinn/training/__init__.py
flowinn/training/loss.py
flowinn/utils/__init__.py
flowinn-1.2.2.dist-info/LICENSE
flowinn-1.2.2.dist-info/METADATA
flowinn-1.2.2.dist-info/WHEEL
flowinn-1.2.2.dist-info/top_level.txt
flowinn-1.2.2.dist-info/RECORD
