Metadata-Version: 2.2
Name: flowinn
Version: 1.2.2
Summary: fl0wINN: Multi-Scale Turbulent Flow Investigation using Neural Networks
Home-page: https://github.com/errasti13/flowINN
Author: Jon Errasti Odriozola
Author-email: errasti13@gmail.com
Classifier: Programming Language :: Python :: 3
Classifier: License :: OSI Approved :: MIT License
Classifier: Operating System :: OS Independent
Requires-Python: >=3.8
License-File: LICENSE
Requires-Dist: numpy>=1.26.4
Requires-Dist: matplotlib>=3.8.3
Requires-Dist: scipy>=1.13.1
Requires-Dist: tensorflow>=2.14.1
Dynamic: author
Dynamic: author-email
Dynamic: classifier
Dynamic: description
Dynamic: description-content-type
Dynamic: home-page
Dynamic: requires-dist
Dynamic: requires-python
Dynamic: summary
